stix_shifter_modules/crowdstrike_logscale/__init__.py
stix_shifter_modules/crowdstrike_logscale/entry_point.py
stix_shifter_modules/crowdstrike_logscale/configuration/config.json
stix_shifter_modules/crowdstrike_logscale/configuration/dialects.json
stix_shifter_modules/crowdstrike_logscale/configuration/lang_en.json
stix_shifter_modules/crowdstrike_logscale/stix_translation/__init__.py
stix_shifter_modules/crowdstrike_logscale/stix_translation/json_to_stix_translator.py
stix_shifter_modules/crowdstrike_logscale/stix_translation/query_constructor.py
stix_shifter_modules/crowdstrike_logscale/stix_translation/query_translator.py
stix_shifter_modules/crowdstrike_logscale/stix_translation/transformers.py
stix_shifter_modules/crowdstrike_logscale/stix_translation/json/config_map.json
stix_shifter_modules/crowdstrike_logscale/stix_translation/json/crowdstrikeedr_from_stix_map.json
stix_shifter_modules/crowdstrike_logscale/stix_translation/json/crowdstrikeedr_to_stix_map.json
stix_shifter_modules/crowdstrike_logscale/stix_translation/json/operators.json
stix_shifter_modules/crowdstrike_logscale/stix_translation/json/stix_2_1/crowdstrikeedr_from_stix_map.json
stix_shifter_modules/crowdstrike_logscale/stix_translation/json/stix_2_1/crowdstrikeedr_to_stix_map.json
stix_shifter_modules/crowdstrike_logscale/stix_transmission/__init__.py
stix_shifter_modules/crowdstrike_logscale/stix_transmission/api_client.py
stix_shifter_modules/crowdstrike_logscale/stix_transmission/delete_connector.py
stix_shifter_modules/crowdstrike_logscale/stix_transmission/error_mapper.py
stix_shifter_modules/crowdstrike_logscale/stix_transmission/ping_connector.py
stix_shifter_modules/crowdstrike_logscale/stix_transmission/query_connector.py
stix_shifter_modules/crowdstrike_logscale/stix_transmission/results_connector.py
stix_shifter_modules/crowdstrike_logscale/stix_transmission/status_connector.py
stix_shifter_modules_crowdstrike_logscale-8.0.2.dist-info/licenses/AUTHORS.md
stix_shifter_modules_crowdstrike_logscale-8.0.2.dist-info/licenses/LICENSE.md
stix_shifter_modules_crowdstrike_logscale-8.0.2.dist-info/licenses/NOTICE
stix_shifter_modules_crowdstrike_logscale-8.0.2.dist-info/METADATA
stix_shifter_modules_crowdstrike_logscale-8.0.2.dist-info/WHEEL
stix_shifter_modules_crowdstrike_logscale-8.0.2.dist-info/top_level.txt
stix_shifter_modules_crowdstrike_logscale-8.0.2.dist-info/RECORD
